{
  "data_base_path": "database/database.db",
  "token": "7004388668:AAEEfvIXpuNwNemcJlt1TaEEZOzD7rwX4tQ",
  "start_text": "Привет! Выберите опцию",
  "user_messages": ["Status", "Priority", "Start Appointment Date", "End Appointment Date", "Applicant Email", "Passport Issue Place", "Passport Expiry Date", "Passport Issue Date", "Passport Number", "Passport Issue Country", "Passport Type", "Date of Birth", "First Name", "Surname", "Mobile number", "Jurisdiction", "Location", "Visa Sub Type", "Appointment Category", "Starting date", "End date", "Surname At Birth", "Place Of Birth", "Country Of Birth", "Current Nationality", "Nationality At Birth", "Gender", "Marital Status", "Travel Date", "Address & Contact Details: Home Address Line1", "Address & Contact Details: Country", "Address & Contact Details: City", "Address & Contact Details: Postal Code", "Address & Contact Details: Contact Number", "Travel Indivation: Purpose Of Journey", "Travel Indivation: Member State Destination", "Travel Indivation: Member State First Entry", "Travel Indivation: Number Of Entries Requested", "Travel Indivation: Intended Stay Duration", "Previous Finger Print Date", "Intended Date Of Arrival", "Intended Date Of Departure", "Details of the inviting person in the member state", "Inviting Organization Details: Name", "Inviting Organization Details: Country", "Inviting Organization Details: City", "Inviting Organization Details: Zip Code", "Inviting Organization Details: Address", "Inviting Organization Details: Email", "Inviting Organization Details: Contact Number", "Contact Person Details: Name", "Contact Person Details: Surname", "Contact Person Details: Country", "Contact Person Details: City", "Contact Person Details: Zip Code", "Contact Person Details: Address", "Contact Person Details: Contact Number", "Contact Person Details: Email"],
  "user_columns": ["Status", "Priority", "StartAppointmentDate", "EndAppointmentDate", "ApplicantEmail", "Place", "Expiry", "IssueDate", "PassportNum", "IssueCountry", "PassportType", "Birth", "FirstName", "Surname", "MobileNumber", "Jurisdiction", "Location", "VisaSubType", "AppointmentCategory", "StartDate", "EndDate", "SurnameAtBirth", "PlaceOfBirth", "CountryOfBirth", "CurrentNationality", "NationalityAtBirth", "Gender", "MaritalStatus", "TravelDate", "HomeAddressLine1", "Country", "City", "PostalCode", "ContactNumber", "PurposeOfJourney", "MemberStateDestination", "MemberStateFirstEntry", "NumberOfEntriesRequested", "IntendedStayDuration", "PreviousFingerPrintDate", "IntendedDateOfArrival", "IntendedDateOfDeparture", "InvitingPerson", "InvitingOrganizationDetailsName", "InvitingOrganizationDetailsCountry", "InvitingOrganizationDetailsCity", "InvitingOrganizationDetailsZipCode", "InvitingOrganizationDetailsAddress", "InvitingOrganizationDetailsEmail", "InvitingOrganizationDetailsContactNumber", "ContactPersonDetailsName", "ContactPersonDetailsSurname", "ContactPersonDetailsCountry", "ContactPersonDetailsCity", "ContactPersonDetailsZipCode", "ContactPersonDetailsAddress", "ContactPersonDetailsContactNumber", "ContactPersonDetailsEmail"],
  "bot_messages": ["Email", "Password of Email", "Password of Account", "Account type", "ip:port", "Login", "Password"],
  "bot_columns": ["Email", "PassEmail", "PassAccount", "IsBot", "IpPort", "Login", "Password"]
}